[
  {
    "symbol": "MHLXMIRU.NS",
    "price": 138.71,
    "market_cap_cr": 147.0,
    "avg_volume": 79884,
    "price_stage": "\ud83d\udfe1 EARLY UPTREND",
    "sector": "FMCG",
    "composite_score": 0.5764,
    "scanned_at": "2026-07-21T15:47:28.728207",
    "dna": {
      "dna_score": 0.482,
      "dna_grade": "C \u2014 Monitor, not yet actionable",
      "dna_flags": [],
      "disqualifiers": [],
      "rev_accel_score": 0.3,
      "rev_accel_desc": "No Screener data",
      "promoter_score": 0.7,
      "promoter_desc": "\ud83d\udc65 Promoter 81% holding, minimal/no pledge \u2014 won't sell",
      "catalyst_score": 0.1,
      "catalyst_desc": "\u26aa No specific catalyst found in BSE announcements",
      "mcap_score": 1.0,
      "mcap_desc": "\u20b9147Cr \u2014 ideal multibagger size (30\u2013150 Cr)",
      "price_stage_score": 0.65,
      "price_stage_desc": "\ud83d\udfe1 Early uptrend (26% above 52W low, 40% below high)",
      "sector_score": 0.45,
      "sector_desc": "\ud83d\udfe1 FMCG: Neutral (-1.3% 3M)",
      "discovery_score": 0.35,
      "discovery_desc": "Institutional ownership data unavailable",
      "sector": "FMCG",
      "market_cap_cr": 147.3138432
    },
    "piotroski_score": 8,
    "piotroski_01": 0.889,
    "lynch_score": 1.0,
    "debt_score": 1.0,
    "group": null,
    "public_data": {
      "insider_net_shares": 0,
      "insider_buy_count": 0,
      "insider_value_cr": 0.0,
      "promoter_buying": false,
      "insider_score": 0.3,
      "pledge_pct": null,
      "promoter_held_pct": 81.4,
      "is_high_pledge": false,
      "pledge_score": 0.5,
      "has_bulk_deal": false,
      "institutional_buying": false,
      "bulk_net_value_cr": 0.0,
      "bulk_score": 0.3,
      "public_score": 0.36,
      "public_flags": []
    },
    "bse_code": null,
    "announcement_count": 0,
    "concall": {
      "concall_score": 0.3,
      "tier1_signals": [],
      "tier2_signals": [],
      "negative_signals": [],
      "concall_flag": null,
      "manual_review": false,
      "concall_count": 0,
      "has_concall_data": false
    },
    "screener": null,
    "screener_flags": [],
    "screener_roce": null,
    "all_flags": [],
    "persistence": {
      "days_in_watchlist": 8,
      "streak": 0,
      "score_trend": "stable",
      "score_7d_delta": -0.001,
      "first_seen": "20260630",
      "peak_score": 0.589,
      "price_since_first_pct": 14.5,
      "all_catalysts": [
        "\ud83d\udfe2 Deep base (near 52W low, 10% above low)",
        "\ud83d\udfe2 Deep base (near 52W low, 19% above low)",
        "\u2b50 FMCG: EARLY UPCYCLE \u2014 recovering from below 200EMA, +4.0% 1M",
        "\ud83d\udfe2 Deep base (near 52W low, 24% above low)"
      ],
      "latest_catalyst_score": 0.1,
      "latest_dna_score": 0.482
    }
  },
  {
    "symbol": "DRCSYSTEMS.NS",
    "price": 13.23,
    "market_cap_cr": 191.0,
    "avg_volume": 59625,
    "price_stage": "\ud83d\udfe2 DEEP BASE",
    "sector": "IT",
    "composite_score": 0.5629,
    "scanned_at": "2026-07-21T15:41:00.591688",
    "dna": {
      "dna_score": 0.526,
      "dna_grade": "C \u2014 Monitor, not yet actionable",
      "dna_flags": [
        "\ud83d\udfe2 DEEP BASE + coiling (near 52W low, ATR contracted) \u2014 ideal entry zone",
        "\u2b50 IT: EARLY UPCYCLE \u2014 recovering from below 200EMA, +4.9% 1M"
      ],
      "disqualifiers": [],
      "rev_accel_score": 0.3,
      "rev_accel_desc": "No Screener data",
      "promoter_score": 0.7,
      "promoter_desc": "\ud83d\udc65 Promoter 74% holding, minimal/no pledge \u2014 won't sell",
      "catalyst_score": 0.1,
      "catalyst_desc": "\u26aa No specific catalyst found in BSE announcements",
      "mcap_score": 0.85,
      "mcap_desc": "\u20b9191Cr \u2014 good headroom for 5\u201310x",
      "price_stage_score": 1.0,
      "price_stage_desc": "\ud83d\udfe2 DEEP BASE + coiling (near 52W low, ATR contracted) \u2014 ideal entry zone",
      "sector_score": 0.9,
      "sector_desc": "\u2b50 IT: EARLY UPCYCLE \u2014 recovering from below 200EMA, +4.9% 1M",
      "discovery_score": 0.35,
      "discovery_desc": "Institutional ownership data unavailable",
      "sector": "IT",
      "market_cap_cr": 190.619584
    },
    "piotroski_score": 5,
    "piotroski_01": 0.556,
    "lynch_score": 1.0,
    "debt_score": 1.0,
    "group": null,
    "public_data": {
      "insider_net_shares": 0,
      "insider_buy_count": 0,
      "insider_value_cr": 0.0,
      "promoter_buying": false,
      "insider_score": 0.3,
      "pledge_pct": null,
      "promoter_held_pct": 74.0,
      "is_high_pledge": false,
      "pledge_score": 0.5,
      "has_bulk_deal": false,
      "institutional_buying": false,
      "bulk_net_value_cr": 0.0,
      "bulk_score": 0.3,
      "public_score": 0.36,
      "public_flags": []
    },
    "bse_code": null,
    "announcement_count": 0,
    "concall": {
      "concall_score": 0.3,
      "tier1_signals": [],
      "tier2_signals": [],
      "negative_signals": [],
      "concall_flag": null,
      "manual_review": false,
      "concall_count": 0,
      "has_concall_data": false
    },
    "screener": null,
    "screener_flags": [],
    "screener_roce": null,
    "all_flags": [
      "\ud83d\udfe2 DEEP BASE + coiling (near 52W low, ATR contracted) \u2014 ideal entry zone",
      "\u2b50 IT: EARLY UPCYCLE \u2014 recovering from below 200EMA, +4.9% 1M"
    ],
    "persistence": {
      "days_in_watchlist": 9,
      "streak": 0,
      "score_trend": "stable",
      "score_7d_delta": 0.013,
      "first_seen": "20260316",
      "peak_score": 0.629,
      "price_since_first_pct": 5.4,
      "all_catalysts": [
        "\ud83d\udfe2 Deep base (near 52W low, 23% above low)",
        "\ud83d\udfe2 Deep base (near 52W low, 21% above low)",
        "\ud83d\udfe2 Deep base (near 52W low, 24% above low)",
        "\ud83d\udfe2 Deep base (near 52W low, 20% above low)",
        "\ud83d\udfe2 Deep base (near 52W low, 22% above low)",
        "\ud83d\udfe2 DEEP BASE + coiling (near 52W low, ATR contracted) \u2014 ideal entry zone",
        "\u2b50 IT: EARLY UPCYCLE \u2014 recovering from below 200EMA, +4.4% 1M",
        "\u2b50 IT: EARLY UPCYCLE \u2014 recovering from below 200EMA, +4.9% 1M"
      ],
      "latest_catalyst_score": 0.1,
      "latest_dna_score": 0.526
    }
  },
  {
    "symbol": "ADROITINFO.NS",
    "price": 9.12,
    "market_cap_cr": 52.0,
    "avg_volume": 43543,
    "price_stage": "\ud83d\udfe2 DEEP BASE",
    "sector": "IT",
    "composite_score": 0.5604,
    "scanned_at": "2026-07-21T15:36:47.224417",
    "dna": {
      "dna_score": 0.511,
      "dna_grade": "C \u2014 Monitor, not yet actionable",
      "dna_flags": [
        "\ud83d\udfe2 DEEP BASE + coiling (near 52W low, ATR contracted) \u2014 ideal entry zone",
        "\u2b50 IT: EARLY UPCYCLE \u2014 recovering from below 200EMA, +4.9% 1M"
      ],
      "disqualifiers": [],
      "rev_accel_score": 0.3,
      "rev_accel_desc": "No Screener data",
      "promoter_score": 0.55,
      "promoter_desc": "\ud83d\udc65 Promoter 51%, low pledge",
      "catalyst_score": 0.1,
      "catalyst_desc": "\u26aa No specific catalyst found in BSE announcements",
      "mcap_score": 1.0,
      "mcap_desc": "\u20b952Cr \u2014 ideal multibagger size (30\u2013150 Cr)",
      "price_stage_score": 1.0,
      "price_stage_desc": "\ud83d\udfe2 DEEP BASE + coiling (near 52W low, ATR contracted) \u2014 ideal entry zone",
      "sector_score": 0.9,
      "sector_desc": "\u2b50 IT: EARLY UPCYCLE \u2014 recovering from below 200EMA, +4.9% 1M",
      "discovery_score": 0.35,
      "discovery_desc": "Institutional ownership data unavailable",
      "sector": "IT",
      "market_cap_cr": 52.2288096
    },
    "piotroski_score": 7,
    "piotroski_01": 0.778,
    "lynch_score": 1.0,
    "debt_score": 1.0,
    "group": null,
    "public_data": {
      "insider_net_shares": 0,
      "insider_buy_count": 0,
      "insider_value_cr": 0.0,
      "promoter_buying": false,
      "insider_score": 0.3,
      "pledge_pct": null,
      "promoter_held_pct": 51.0,
      "is_high_pledge": false,
      "pledge_score": 0.5,
      "has_bulk_deal": false,
      "institutional_buying": false,
      "bulk_net_value_cr": 0.0,
      "bulk_score": 0.3,
      "public_score": 0.36,
      "public_flags": []
    },
    "bse_code": null,
    "announcement_count": 0,
    "concall": {
      "concall_score": 0.3,
      "tier1_signals": [],
      "tier2_signals": [],
      "negative_signals": [],
      "concall_flag": null,
      "manual_review": false,
      "concall_count": 0,
      "has_concall_data": false
    },
    "screener": null,
    "screener_flags": [],
    "screener_roce": null,
    "all_flags": [
      "\ud83d\udfe2 DEEP BASE + coiling (near 52W low, ATR contracted) \u2014 ideal entry zone",
      "\u2b50 IT: EARLY UPCYCLE \u2014 recovering from below 200EMA, +4.9% 1M"
    ],
    "persistence": {
      "days_in_watchlist": 7,
      "streak": 0,
      "score_trend": "stable",
      "score_7d_delta": 0.017,
      "first_seen": "20260505",
      "peak_score": 0.56,
      "price_since_first_pct": -8.5,
      "all_catalysts": [
        "\ud83d\udfe2 Deep base (near 52W low, 21% above low)",
        "\ud83d\udfe2 Deep base (near 52W low, 7% above low)",
        "\ud83d\udfe2 Deep base (near 52W low, 12% above low)",
        "\ud83d\udfe2 Deep base (near 52W low, 13% above low)",
        "\ud83d\udfe2 Deep base (near 52W low, 11% above low)",
        "\ud83d\udfe2 Deep base (near 52W low, 9% above low)",
        "\ud83d\udfe2 DEEP BASE + coiling (near 52W low, ATR contracted) \u2014 ideal entry zone",
        "\u2b50 IT: EARLY UPCYCLE \u2014 recovering from below 200EMA, +4.4% 1M",
        "\u2b50 IT: EARLY UPCYCLE \u2014 recovering from below 200EMA, +4.9% 1M"
      ],
      "latest_catalyst_score": 0.1,
      "latest_dna_score": 0.511
    }
  },
  {
    "symbol": "MEDICO.NS",
    "price": 38.62,
    "market_cap_cr": 320.0,
    "avg_volume": 231841,
    "price_stage": "\ud83d\udfe2 DEEP BASE",
    "sector": "Pharma",
    "composite_score": 0.5531,
    "scanned_at": "2026-07-21T15:47:21.907242",
    "dna": {
      "dna_score": 0.502,
      "dna_grade": "C \u2014 Monitor, not yet actionable",
      "dna_flags": [
        "\ud83d\udfe2 Deep base (near 52W low, 18% above low)"
      ],
      "disqualifiers": [],
      "rev_accel_score": 0.3,
      "rev_accel_desc": "No Screener data",
      "promoter_score": 0.7,
      "promoter_desc": "\ud83d\udc65 Promoter 69% holding, minimal/no pledge \u2014 won't sell",
      "catalyst_score": 0.1,
      "catalyst_desc": "\u26aa No specific catalyst found in BSE announcements",
      "mcap_score": 0.85,
      "mcap_desc": "\u20b9320Cr \u2014 good headroom for 5\u201310x",
      "price_stage_score": 0.85,
      "price_stage_desc": "\ud83d\udfe2 Deep base (near 52W low, 18% above low)",
      "sector_score": 0.75,
      "sector_desc": "\u2705 Pharma: Bull trend, above 200EMA, +16.3% 3M",
      "discovery_score": 0.35,
      "discovery_desc": "Institutional ownership data unavailable",
      "sector": "Pharma",
      "market_cap_cr": 320.4841984
    },
    "piotroski_score": 7,
    "piotroski_01": 0.778,
    "lynch_score": 0.91,
    "debt_score": 0.65,
    "group": null,
    "public_data": {
      "insider_net_shares": 0,
      "insider_buy_count": 0,
      "insider_value_cr": 0.0,
      "promoter_buying": false,
      "insider_score": 0.3,
      "pledge_pct": null,
      "promoter_held_pct": 69.4,
      "is_high_pledge": false,
      "pledge_score": 0.5,
      "has_bulk_deal": false,
      "institutional_buying": false,
      "bulk_net_value_cr": 0.0,
      "bulk_score": 0.3,
      "public_score": 0.36,
      "public_flags": []
    },
    "bse_code": null,
    "announcement_count": 0,
    "concall": {
      "concall_score": 0.3,
      "tier1_signals": [],
      "tier2_signals": [],
      "negative_signals": [],
      "concall_flag": null,
      "manual_review": false,
      "concall_count": 0,
      "has_concall_data": false
    },
    "screener": null,
    "screener_flags": [],
    "screener_roce": null,
    "all_flags": [
      "\ud83d\udfe2 Deep base (near 52W low, 18% above low)"
    ],
    "persistence": {
      "days_in_watchlist": 10,
      "streak": 0,
      "score_trend": "stable",
      "score_7d_delta": 0.007,
      "first_seen": "20260407",
      "peak_score": 0.553,
      "price_since_first_pct": -2.4,
      "all_catalysts": [
        "\ud83d\udfe2 Deep base (near 52W low, 21% above low)",
        "\ud83d\udfe2 Deep base (near 52W low, 23% above low)",
        "\ud83d\udfe2 Deep base (near 52W low, 22% above low)",
        "\ud83d\udfe2 Deep base (near 52W low, 18% above low)",
        "\ud83d\udfe2 Deep base (near 52W low, 20% above low)"
      ],
      "latest_catalyst_score": 0.1,
      "latest_dna_score": 0.502
    }
  },
  {
    "symbol": "CINEVISTA.NS",
    "price": 15.0,
    "market_cap_cr": 86.0,
    "avg_volume": 33486,
    "price_stage": "\ud83d\udfe2 DEEP BASE",
    "sector": "Other",
    "composite_score": 0.5502,
    "scanned_at": "2026-07-21T15:39:55.672187",
    "dna": {
      "dna_score": 0.505,
      "dna_grade": "C \u2014 Monitor, not yet actionable",
      "dna_flags": [
        "\ud83d\udfe2 Deep base (near 52W low, 14% above low)"
      ],
      "disqualifiers": [],
      "rev_accel_score": 0.3,
      "rev_accel_desc": "No Screener data",
      "promoter_score": 0.7,
      "promoter_desc": "\ud83d\udc65 Promoter 74% holding, minimal/no pledge \u2014 won't sell",
      "catalyst_score": 0.1,
      "catalyst_desc": "\u26aa No specific catalyst found in BSE announcements",
      "mcap_score": 1.0,
      "mcap_desc": "\u20b986Cr \u2014 ideal multibagger size (30\u2013150 Cr)",
      "price_stage_score": 0.85,
      "price_stage_desc": "\ud83d\udfe2 Deep base (near 52W low, 14% above low)",
      "sector_score": 0.5,
      "sector_desc": "Sector 'Other' not mapped",
      "discovery_score": 0.35,
      "discovery_desc": "Institutional ownership data unavailable",
      "sector": "Other",
      "market_cap_cr": 86.1547136
    },
    "piotroski_score": 9,
    "piotroski_01": 1.0,
    "lynch_score": 0.58,
    "debt_score": 0.65,
    "group": null,
    "public_data": {
      "insider_net_shares": 0,
      "insider_buy_count": 0,
      "insider_value_cr": 0.0,
      "promoter_buying": false,
      "insider_score": 0.3,
      "pledge_pct": null,
      "promoter_held_pct": 73.6,
      "is_high_pledge": false,
      "pledge_score": 0.5,
      "has_bulk_deal": false,
      "institutional_buying": false,
      "bulk_net_value_cr": 0.0,
      "bulk_score": 0.3,
      "public_score": 0.36,
      "public_flags": []
    },
    "bse_code": null,
    "announcement_count": 0,
    "concall": {
      "concall_score": 0.3,
      "tier1_signals": [],
      "tier2_signals": [],
      "negative_signals": [],
      "concall_flag": null,
      "manual_review": false,
      "concall_count": 0,
      "has_concall_data": false
    },
    "screener": null,
    "screener_flags": [],
    "screener_roce": null,
    "all_flags": [
      "\ud83d\udfe2 Deep base (near 52W low, 14% above low)"
    ],
    "persistence": {
      "days_in_watchlist": 8,
      "streak": 0,
      "score_trend": "stable",
      "score_7d_delta": 0.0,
      "first_seen": "20260701",
      "peak_score": 0.55,
      "price_since_first_pct": -13.6,
      "all_catalysts": [
        "\ud83d\udfe2 Deep base (near 52W low, 22% above low)",
        "\ud83d\udfe2 Deep base (near 52W low, 20% above low)",
        "\ud83d\udfe2 Deep base (near 52W low, 18% above low)",
        "\ud83d\udfe2 Deep base (near 52W low, 16% above low)",
        "\ud83d\udfe2 Deep base (near 52W low, 14% above low)"
      ],
      "latest_catalyst_score": 0.1,
      "latest_dna_score": 0.505
    }
  },
  {
    "symbol": "ASMS.NS",
    "price": 7.11,
    "market_cap_cr": 217.0,
    "avg_volume": 695226,
    "price_stage": "\ud83d\udfe2 DEEP BASE",
    "sector": "IT",
    "composite_score": 0.5489,
    "scanned_at": "2026-07-21T15:37:43.745255",
    "dna": {
      "dna_score": 0.526,
      "dna_grade": "C \u2014 Monitor, not yet actionable",
      "dna_flags": [
        "\ud83d\udfe2 DEEP BASE + coiling (near 52W low, ATR contracted) \u2014 ideal entry zone",
        "\u2b50 IT: EARLY UPCYCLE \u2014 recovering from below 200EMA, +4.9% 1M"
      ],
      "disqualifiers": [],
      "rev_accel_score": 0.3,
      "rev_accel_desc": "No Screener data",
      "promoter_score": 0.7,
      "promoter_desc": "\ud83d\udc65 Promoter 68% holding, minimal/no pledge \u2014 won't sell",
      "catalyst_score": 0.1,
      "catalyst_desc": "\u26aa No specific catalyst found in BSE announcements",
      "mcap_score": 0.85,
      "mcap_desc": "\u20b9217Cr \u2014 good headroom for 5\u201310x",
      "price_stage_score": 1.0,
      "price_stage_desc": "\ud83d\udfe2 DEEP BASE + coiling (near 52W low, ATR contracted) \u2014 ideal entry zone",
      "sector_score": 0.9,
      "sector_desc": "\u2b50 IT: EARLY UPCYCLE \u2014 recovering from below 200EMA, +4.9% 1M",
      "discovery_score": 0.35,
      "discovery_desc": "Institutional ownership data unavailable",
      "sector": "IT",
      "market_cap_cr": 216.5540608
    },
    "piotroski_score": 5,
    "piotroski_01": 0.556,
    "lynch_score": 1.0,
    "debt_score": 0.65,
    "group": null,
    "public_data": {
      "insider_net_shares": 0,
      "insider_buy_count": 0,
      "insider_value_cr": 0.0,
      "promoter_buying": false,
      "insider_score": 0.3,
      "pledge_pct": null,
      "promoter_held_pct": 67.5,
      "is_high_pledge": false,
      "pledge_score": 0.5,
      "has_bulk_deal": false,
      "institutional_buying": false,
      "bulk_net_value_cr": 0.0,
      "bulk_score": 0.3,
      "public_score": 0.36,
      "public_flags": []
    },
    "bse_code": null,
    "announcement_count": 0,
    "concall": {
      "concall_score": 0.3,
      "tier1_signals": [],
      "tier2_signals": [],
      "negative_signals": [],
      "concall_flag": null,
      "manual_review": false,
      "concall_count": 0,
      "has_concall_data": false
    },
    "screener": null,
    "screener_flags": [],
    "screener_roce": null,
    "all_flags": [
      "\ud83d\udfe2 DEEP BASE + coiling (near 52W low, ATR contracted) \u2014 ideal entry zone",
      "\u2b50 IT: EARLY UPCYCLE \u2014 recovering from below 200EMA, +4.9% 1M"
    ],
    "persistence": {
      "days_in_watchlist": 9,
      "streak": 0,
      "score_trend": "stable",
      "score_7d_delta": 0.008,
      "first_seen": "20260609",
      "peak_score": 0.549,
      "price_since_first_pct": -2.2,
      "all_catalysts": [
        "\ud83d\udfe2 DEEP BASE + coiling (near 52W low, ATR contracted) \u2014 ideal entry zone",
        "\u2b50 IT: EARLY UPCYCLE \u2014 recovering from below 200EMA, +4.4% 1M",
        "\u2b50 IT: EARLY UPCYCLE \u2014 recovering from below 200EMA, +4.9% 1M"
      ],
      "latest_catalyst_score": 0.1,
      "latest_dna_score": 0.526
    }
  },
  {
    "symbol": "XCHANGING.NS",
    "price": 64.45,
    "market_cap_cr": 718.0,
    "avg_volume": 94530,
    "price_stage": "\ud83d\udfe1 EARLY UPTREND",
    "sector": "IT",
    "composite_score": 0.5477,
    "scanned_at": "2026-07-21T15:55:40.174241",
    "dna": {
      "dna_score": 0.493,
      "dna_grade": "C \u2014 Monitor, not yet actionable",
      "dna_flags": [
        "\u2b50 IT: EARLY UPCYCLE \u2014 recovering from below 200EMA, +4.9% 1M",
        "\ud83d\udc41\ufe0f UNDISCOVERED: 0.0% institutional \u2014 Lynch sweet spot"
      ],
      "disqualifiers": [],
      "rev_accel_score": 0.3,
      "rev_accel_desc": "No Screener data",
      "promoter_score": 0.7,
      "promoter_desc": "\ud83d\udc65 Promoter 75% holding, minimal/no pledge \u2014 won't sell",
      "catalyst_score": 0.1,
      "catalyst_desc": "\u26aa No specific catalyst found in BSE announcements",
      "mcap_score": 0.65,
      "mcap_desc": "\u20b9718Cr \u2014 moderate headroom for 3\u20135x",
      "price_stage_score": 0.65,
      "price_stage_desc": "\ud83d\udfe1 Early uptrend (35% above 52W low, 34% below high)",
      "sector_score": 0.9,
      "sector_desc": "\u2b50 IT: EARLY UPCYCLE \u2014 recovering from below 200EMA, +4.9% 1M",
      "discovery_score": 1.0,
      "discovery_desc": "\ud83d\udc41\ufe0f UNDISCOVERED: 0.0% institutional \u2014 Lynch sweet spot",
      "sector": "IT",
      "market_cap_cr": 717.9969024
    },
    "piotroski_score": 8,
    "piotroski_01": 0.889,
    "lynch_score": 0.58,
    "debt_score": 1.0,
    "group": null,
    "public_data": {
      "insider_net_shares": 0,
      "insider_buy_count": 0,
      "insider_value_cr": 0.0,
      "promoter_buying": false,
      "insider_score": 0.3,
      "pledge_pct": null,
      "promoter_held_pct": 75.0,
      "is_high_pledge": false,
      "pledge_score": 0.5,
      "has_bulk_deal": false,
      "institutional_buying": false,
      "bulk_net_value_cr": 0.0,
      "bulk_score": 0.3,
      "public_score": 0.36,
      "public_flags": []
    },
    "bse_code": null,
    "announcement_count": 0,
    "concall": {
      "concall_score": 0.3,
      "tier1_signals": [],
      "tier2_signals": [],
      "negative_signals": [],
      "concall_flag": null,
      "manual_review": false,
      "concall_count": 0,
      "has_concall_data": false
    },
    "screener": null,
    "screener_flags": [],
    "screener_roce": null,
    "all_flags": [
      "\u2b50 IT: EARLY UPCYCLE \u2014 recovering from below 200EMA, +4.9% 1M",
      "\ud83d\udc41\ufe0f UNDISCOVERED: 0.0% institutional \u2014 Lynch sweet spot"
    ],
    "persistence": {
      "days_in_watchlist": 8,
      "streak": 0,
      "score_trend": "stable",
      "score_7d_delta": 0.004,
      "first_seen": "20260401",
      "peak_score": 0.551,
      "price_since_first_pct": 21.3,
      "all_catalysts": [
        "\ud83d\udfe2 Deep base (near 52W low, 11% above low)",
        "\ud83d\udc41\ufe0f UNDISCOVERED: 0.0% institutional \u2014 Lynch sweet spot",
        "\ud83d\udfe2 Deep base (near 52W low, 20% above low)",
        "\u2b50 IT: EARLY UPCYCLE \u2014 recovering from below 200EMA, +4.4% 1M",
        "\u2b50 IT: EARLY UPCYCLE \u2014 recovering from below 200EMA, +2.7% 1M",
        "\u2b50 IT: EARLY UPCYCLE \u2014 recovering from below 200EMA, +4.9% 1M"
      ],
      "latest_catalyst_score": 0.1,
      "latest_dna_score": 0.493
    }
  },
  {
    "symbol": "VGL.NS",
    "price": 61.69,
    "market_cap_cr": 318.0,
    "avg_volume": 193584,
    "price_stage": "\ud83d\udfe1 EARLY UPTREND",
    "sector": "FMCG",
    "composite_score": 0.5461,
    "scanned_at": "2026-07-21T15:55:01.730341",
    "dna": {
      "dna_score": 0.464,
      "dna_grade": "C \u2014 Monitor, not yet actionable",
      "dna_flags": [],
      "disqualifiers": [],
      "rev_accel_score": 0.3,
      "rev_accel_desc": "No Screener data",
      "promoter_score": 0.7,
      "promoter_desc": "\ud83d\udc65 Promoter 69% holding, minimal/no pledge \u2014 won't sell",
      "catalyst_score": 0.1,
      "catalyst_desc": "\u26aa No specific catalyst found in BSE announcements",
      "mcap_score": 0.85,
      "mcap_desc": "\u20b9318Cr \u2014 good headroom for 5\u201310x",
      "price_stage_score": 0.65,
      "price_stage_desc": "\ud83d\udfe1 Early uptrend (31% above 52W low, 35% below high)",
      "sector_score": 0.45,
      "sector_desc": "\ud83d\udfe1 FMCG: Neutral (-1.3% 3M)",
      "discovery_score": 0.35,
      "discovery_desc": "Institutional ownership data unavailable",
      "sector": "FMCG",
      "market_cap_cr": 317.8804224
    },
    "piotroski_score": 6,
    "piotroski_01": 0.667,
    "lynch_score": 1.0,
    "debt_score": 1.0,
    "group": null,
    "public_data": {
      "insider_net_shares": 0,
      "insider_buy_count": 0,
      "insider_value_cr": 0.0,
      "promoter_buying": false,
      "insider_score": 0.3,
      "pledge_pct": null,
      "promoter_held_pct": 69.1,
      "is_high_pledge": false,
      "pledge_score": 0.5,
      "has_bulk_deal": false,
      "institutional_buying": false,
      "bulk_net_value_cr": 0.0,
      "bulk_score": 0.3,
      "public_score": 0.36,
      "public_flags": []
    },
    "bse_code": null,
    "announcement_count": 0,
    "concall": {
      "concall_score": 0.3,
      "tier1_signals": [],
      "tier2_signals": [],
      "negative_signals": [],
      "concall_flag": null,
      "manual_review": false,
      "concall_count": 0,
      "has_concall_data": false
    },
    "screener": null,
    "screener_flags": [],
    "screener_roce": null,
    "all_flags": [],
    "persistence": {
      "days_in_watchlist": 10,
      "streak": 0,
      "score_trend": "stable",
      "score_7d_delta": -0.004,
      "first_seen": "20260401",
      "peak_score": 0.566,
      "price_since_first_pct": 21.2,
      "all_catalysts": [
        "\ud83d\udfe2 Deep base (near 52W low, 8% above low)",
        "\u2b50 FMCG: EARLY UPCYCLE \u2014 recovering from below 200EMA, +2.5% 1M",
        "\u2b50 FMCG: EARLY UPCYCLE \u2014 recovering from below 200EMA, +8.8% 1M",
        "\u2b50 FMCG: EARLY UPCYCLE \u2014 recovering from below 200EMA, +7.6% 1M",
        "\u2b50 FMCG: EARLY UPCYCLE \u2014 recovering from below 200EMA, +12.2% 1M",
        "\u2b50 FMCG: EARLY UPCYCLE \u2014 recovering from below 200EMA, +10.4% 1M",
        "\u2b50 FMCG: EARLY UPCYCLE \u2014 recovering from below 200EMA, +7.5% 1M",
        "\u2b50 FMCG: EARLY UPCYCLE \u2014 recovering from below 200EMA, +5.5% 1M",
        "\u2b50 FMCG: EARLY UPCYCLE \u2014 recovering from below 200EMA, +2.7% 1M",
        "\u2b50 FMCG: EARLY UPCYCLE \u2014 recovering from below 200EMA, +4.0% 1M"
      ],
      "latest_catalyst_score": 0.1,
      "latest_dna_score": 0.464
    }
  },
  {
    "symbol": "RAJTV.NS",
    "price": 12.0,
    "market_cap_cr": 62.0,
    "avg_volume": 74461,
    "price_stage": "\ud83d\udfe2 DEEP BASE",
    "sector": "Other",
    "composite_score": 0.5459,
    "scanned_at": "2026-07-21T15:50:05.170484",
    "dna": {
      "dna_score": 0.52,
      "dna_grade": "C \u2014 Monitor, not yet actionable",
      "dna_flags": [
        "\ud83d\udfe2 DEEP BASE + coiling (near 52W low, ATR contracted) \u2014 ideal entry zone"
      ],
      "disqualifiers": [],
      "rev_accel_score": 0.3,
      "rev_accel_desc": "No Screener data",
      "promoter_score": 0.7,
      "promoter_desc": "\ud83d\udc65 Promoter 91% holding, minimal/no pledge \u2014 won't sell",
      "catalyst_score": 0.1,
      "catalyst_desc": "\u26aa No specific catalyst found in BSE announcements",
      "mcap_score": 1.0,
      "mcap_desc": "\u20b962Cr \u2014 ideal multibagger size (30\u2013150 Cr)",
      "price_stage_score": 1.0,
      "price_stage_desc": "\ud83d\udfe2 DEEP BASE + coiling (near 52W low, ATR contracted) \u2014 ideal entry zone",
      "sector_score": 0.5,
      "sector_desc": "Sector 'Other' not mapped",
      "discovery_score": 0.35,
      "discovery_desc": "Institutional ownership data unavailable",
      "sector": "Other",
      "market_cap_cr": 62.2960128
    },
    "piotroski_score": 8,
    "piotroski_01": 0.889,
    "lynch_score": 0.58,
    "debt_score": 0.65,
    "group": null,
    "public_data": {
      "insider_net_shares": 0,
      "insider_buy_count": 0,
      "insider_value_cr": 0.0,
      "promoter_buying": false,
      "insider_score": 0.3,
      "pledge_pct": null,
      "promoter_held_pct": 90.7,
      "is_high_pledge": false,
      "pledge_score": 0.5,
      "has_bulk_deal": false,
      "institutional_buying": false,
      "bulk_net_value_cr": 0.0,
      "bulk_score": 0.3,
      "public_score": 0.36,
      "public_flags": []
    },
    "bse_code": null,
    "announcement_count": 0,
    "concall": {
      "concall_score": 0.3,
      "tier1_signals": [],
      "tier2_signals": [],
      "negative_signals": [],
      "concall_flag": null,
      "manual_review": false,
      "concall_count": 0,
      "has_concall_data": false
    },
    "screener": null,
    "screener_flags": [],
    "screener_roce": null,
    "all_flags": [
      "\ud83d\udfe2 DEEP BASE + coiling (near 52W low, ATR contracted) \u2014 ideal entry zone"
    ],
    "persistence": {
      "days_in_watchlist": 11,
      "streak": 0,
      "score_trend": "stable",
      "score_7d_delta": 0.0,
      "first_seen": "20260526",
      "peak_score": 0.546,
      "price_since_first_pct": -42.8,
      "all_catalysts": [
        "\ud83d\udfe2 DEEP BASE + coiling (near 52W low, ATR contracted) \u2014 ideal entry zone"
      ],
      "latest_catalyst_score": 0.1,
      "latest_dna_score": 0.52
    }
  },
  {
    "symbol": "SAURASHCEM.NS",
    "price": 59.15,
    "market_cap_cr": 658.0,
    "avg_volume": 142553,
    "price_stage": "\ud83d\udfe2 DEEP BASE",
    "sector": "Other",
    "composite_score": 0.5459,
    "scanned_at": "2026-07-21T15:51:14.826156",
    "dna": {
      "dna_score": 0.489,
      "dna_grade": "C \u2014 Monitor, not yet actionable",
      "dna_flags": [
        "\ud83d\udfe2 Deep base (near 52W low, 23% above low)",
        "\ud83d\udc41\ufe0f UNDISCOVERED: 0.0% institutional \u2014 Lynch sweet spot"
      ],
      "disqualifiers": [],
      "rev_accel_score": 0.3,
      "rev_accel_desc": "No Screener data",
      "promoter_score": 0.7,
      "promoter_desc": "\ud83d\udc65 Promoter 70% holding, minimal/no pledge \u2014 won't sell",
      "catalyst_score": 0.1,
      "catalyst_desc": "\u26aa No specific catalyst found in BSE announcements",
      "mcap_score": 0.65,
      "mcap_desc": "\u20b9658Cr \u2014 moderate headroom for 3\u20135x",
      "price_stage_score": 0.85,
      "price_stage_desc": "\ud83d\udfe2 Deep base (near 52W low, 23% above low)",
      "sector_score": 0.5,
      "sector_desc": "Sector 'Other' not mapped",
      "discovery_score": 1.0,
      "discovery_desc": "\ud83d\udc41\ufe0f UNDISCOVERED: 0.0% institutional \u2014 Lynch sweet spot",
      "sector": "Other",
      "market_cap_cr": 658.3486464
    },
    "piotroski_score": 8,
    "piotroski_01": 0.889,
    "lynch_score": 0.58,
    "debt_score": 1.0,
    "group": null,
    "public_data": {
      "insider_net_shares": 0,
      "insider_buy_count": 0,
      "insider_value_cr": 0.0,
      "promoter_buying": false,
      "insider_score": 0.3,
      "pledge_pct": null,
      "promoter_held_pct": 69.5,
      "is_high_pledge": false,
      "pledge_score": 0.5,
      "has_bulk_deal": false,
      "institutional_buying": false,
      "bulk_net_value_cr": 0.0,
      "bulk_score": 0.3,
      "public_score": 0.36,
      "public_flags": []
    },
    "bse_code": null,
    "announcement_count": 0,
    "concall": {
      "concall_score": 0.3,
      "tier1_signals": [],
      "tier2_signals": [],
      "negative_signals": [],
      "concall_flag": null,
      "manual_review": false,
      "concall_count": 0,
      "has_concall_data": false
    },
    "screener": null,
    "screener_flags": [],
    "screener_roce": null,
    "all_flags": [
      "\ud83d\udfe2 Deep base (near 52W low, 23% above low)",
      "\ud83d\udc41\ufe0f UNDISCOVERED: 0.0% institutional \u2014 Lynch sweet spot"
    ],
    "persistence": {
      "days_in_watchlist": 10,
      "streak": 0,
      "score_trend": "stable",
      "score_7d_delta": 0.0,
      "first_seen": "20260526",
      "peak_score": 0.553,
      "price_since_first_pct": -1.7,
      "all_catalysts": [
        "\ud83d\udfe2 Deep base (near 52W low, 25% above low)",
        "\ud83d\udc41\ufe0f UNDISCOVERED: 0.0% institutional \u2014 Lynch sweet spot",
        "\ud83d\udfe2 Deep base (near 52W low, 24% above low)",
        "\ud83d\udfe2 Deep base (near 52W low, 21% above low)",
        "\ud83d\udfe2 Deep base (near 52W low, 23% above low)",
        "\ud83d\udfe2 Deep base (near 52W low, 22% above low)",
        "\ud83d\udfe2 DEEP BASE + coiling (near 52W low, ATR contracted) \u2014 ideal entry zone",
        "\ud83d\udfe2 Deep base (near 52W low, 18% above low)",
        "\ud83d\udfe2 Deep base (near 52W low, 16% above low)",
        "\ud83d\udfe2 Deep base (near 52W low, 17% above low)",
        "\ud83d\udfe2 Deep base (near 52W low, 14% above low)",
        "\ud83d\udfe2 Deep base (near 52W low, 13% above low)"
      ],
      "latest_catalyst_score": 0.1,
      "latest_dna_score": 0.489
    }
  },
  {
    "symbol": "FABTECH.NS",
    "price": 149.75,
    "market_cap_cr": 666.0,
    "avg_volume": 409437,
    "price_stage": "\ud83d\udfe2 DEEP BASE",
    "sector": "Pharma",
    "composite_score": 0.5458,
    "scanned_at": "2026-07-21T15:42:10.863262",
    "dna": {
      "dna_score": 0.504,
      "dna_grade": "C \u2014 Monitor, not yet actionable",
      "dna_flags": [
        "\ud83d\udfe2 Deep base (near 52W low, 12% above low)",
        "\ud83d\udc41\ufe0f UNDISCOVERED: 1.2% institutional \u2014 Lynch sweet spot"
      ],
      "disqualifiers": [],
      "rev_accel_score": 0.3,
      "rev_accel_desc": "No Screener data",
      "promoter_score": 0.7,
      "promoter_desc": "\ud83d\udc65 Promoter 72% holding, minimal/no pledge \u2014 won't sell",
      "catalyst_score": 0.1,
      "catalyst_desc": "\u26aa No specific catalyst found in BSE announcements",
      "mcap_score": 0.65,
      "mcap_desc": "\u20b9666Cr \u2014 moderate headroom for 3\u20135x",
      "price_stage_score": 0.85,
      "price_stage_desc": "\ud83d\udfe2 Deep base (near 52W low, 12% above low)",
      "sector_score": 0.75,
      "sector_desc": "\u2705 Pharma: Bull trend, above 200EMA, +16.3% 3M",
      "discovery_score": 1.0,
      "discovery_desc": "\ud83d\udc41\ufe0f UNDISCOVERED: 1.2% institutional \u2014 Lynch sweet spot",
      "sector": "Pharma",
      "market_cap_cr": 665.6505856
    },
    "piotroski_score": 5,
    "piotroski_01": 0.556,
    "lynch_score": 0.91,
    "debt_score": 1.0,
    "group": null,
    "public_data": {
      "insider_net_shares": 0,
      "insider_buy_count": 0,
      "insider_value_cr": 0.0,
      "promoter_buying": false,
      "insider_score": 0.3,
      "pledge_pct": null,
      "promoter_held_pct": 72.0,
      "is_high_pledge": false,
      "pledge_score": 0.5,
      "has_bulk_deal": false,
      "institutional_buying": false,
      "bulk_net_value_cr": 0.0,
      "bulk_score": 0.3,
      "public_score": 0.36,
      "public_flags": []
    },
    "bse_code": null,
    "announcement_count": 0,
    "concall": {
      "concall_score": 0.3,
      "tier1_signals": [],
      "tier2_signals": [],
      "negative_signals": [],
      "concall_flag": null,
      "manual_review": false,
      "concall_count": 0,
      "has_concall_data": false
    },
    "screener": null,
    "screener_flags": [],
    "screener_roce": null,
    "all_flags": [
      "\ud83d\udfe2 Deep base (near 52W low, 12% above low)",
      "\ud83d\udc41\ufe0f UNDISCOVERED: 1.2% institutional \u2014 Lynch sweet spot"
    ],
    "persistence": {
      "days_in_watchlist": 16,
      "streak": 0,
      "score_trend": "stable",
      "score_7d_delta": 0.0,
      "first_seen": "20260511",
      "peak_score": 0.546,
      "price_since_first_pct": -11.6,
      "all_catalysts": [
        "\ud83d\udc41\ufe0f UNDISCOVERED: 0.0% institutional \u2014 Lynch sweet spot",
        "\ud83d\udfe2 Deep base (near 52W low, 14% above low)",
        "\ud83d\udc41\ufe0f UNDISCOVERED: 1.2% institutional \u2014 Lynch sweet spot",
        "\ud83d\udfe2 Deep base (near 52W low, 11% above low)",
        "\ud83d\udfe2 Deep base (near 52W low, 12% above low)",
        "\ud83d\udfe2 Deep base (near 52W low, 17% above low)",
        "\ud83d\udfe2 Deep base (near 52W low, 16% above low)",
        "\ud83d\udfe2 Deep base (near 52W low, 10% above low)",
        "\ud83d\udfe2 Deep base (near 52W low, 8% above low)",
        "\ud83d\udfe2 Deep base (near 52W low, 9% above low)",
        "\ud83d\udfe2 Deep base (near 52W low, 18% above low)",
        "\ud83d\udfe2 Deep base (near 52W low, 24% above low)",
        "\ud83d\udfe2 Deep base (near 52W low, 21% above low)",
        "\ud83d\udfe2 Deep base (near 52W low, 20% above low)",
        "\ud83d\udfe2 Deep base (near 52W low, 15% above low)"
      ],
      "latest_catalyst_score": 0.1,
      "latest_dna_score": 0.504
    }
  },
  {
    "symbol": "PLAZACABLE.NS",
    "price": 42.7,
    "market_cap_cr": 187.0,
    "avg_volume": 94917,
    "price_stage": "\ud83d\udfe1 EARLY UPTREND",
    "sector": "Other",
    "composite_score": 0.5445,
    "scanned_at": "2026-07-21T15:49:25.339862",
    "dna": {
      "dna_score": 0.467,
      "dna_grade": "C \u2014 Monitor, not yet actionable",
      "dna_flags": [],
      "disqualifiers": [],
      "rev_accel_score": 0.3,
      "rev_accel_desc": "No Screener data",
      "promoter_score": 0.7,
      "promoter_desc": "\ud83d\udc65 Promoter 70% holding, minimal/no pledge \u2014 won't sell",
      "catalyst_score": 0.1,
      "catalyst_desc": "\u26aa No specific catalyst found in BSE announcements",
      "mcap_score": 0.85,
      "mcap_desc": "\u20b9187Cr \u2014 good headroom for 5\u201310x",
      "price_stage_score": 0.65,
      "price_stage_desc": "\ud83d\udfe1 Early uptrend (52% above 52W low, 32% below high)",
      "sector_score": 0.5,
      "sector_desc": "Sector 'Other' not mapped",
      "discovery_score": 0.35,
      "discovery_desc": "Institutional ownership data unavailable",
      "sector": "Other",
      "market_cap_cr": 186.8213888
    },
    "piotroski_score": 7,
    "piotroski_01": 0.778,
    "lynch_score": 1.0,
    "debt_score": 0.65,
    "group": null,
    "public_data": {
      "insider_net_shares": 0,
      "insider_buy_count": 0,
      "insider_value_cr": 0.0,
      "promoter_buying": false,
      "insider_score": 0.3,
      "pledge_pct": null,
      "promoter_held_pct": 69.8,
      "is_high_pledge": false,
      "pledge_score": 0.5,
      "has_bulk_deal": false,
      "institutional_buying": false,
      "bulk_net_value_cr": 0.0,
      "bulk_score": 0.3,
      "public_score": 0.36,
      "public_flags": []
    },
    "bse_code": null,
    "announcement_count": 0,
    "concall": {
      "concall_score": 0.3,
      "tier1_signals": [],
      "tier2_signals": [],
      "negative_signals": [],
      "concall_flag": null,
      "manual_review": false,
      "concall_count": 0,
      "has_concall_data": false
    },
    "screener": null,
    "screener_flags": [],
    "screener_roce": null,
    "all_flags": [],
    "persistence": {
      "days_in_watchlist": 2,
      "streak": 0,
      "score_trend": "stable",
      "score_7d_delta": 0.005,
      "first_seen": "20260401",
      "peak_score": 0.554,
      "price_since_first_pct": 33.4,
      "all_catalysts": [
        "\ud83d\udfe2 Deep base (near 52W low, 14% above low)",
        "\ud83d\udfe2 Deep base (near 52W low, 16% above low)"
      ],
      "latest_catalyst_score": 0.1,
      "latest_dna_score": 0.467
    }
  },
  {
    "symbol": "CHEMCON.NS",
    "price": 181.06,
    "market_cap_cr": 663.0,
    "avg_volume": 119361,
    "price_stage": "\ud83d\udfe1 EARLY UPTREND",
    "sector": "Other",
    "composite_score": 0.5411,
    "scanned_at": "2026-07-21T15:39:51.967247",
    "dna": {
      "dna_score": 0.469,
      "dna_grade": "C \u2014 Monitor, not yet actionable",
      "dna_flags": [
        "\ud83d\udc41\ufe0f UNDISCOVERED: 0.0% institutional \u2014 Lynch sweet spot"
      ],
      "disqualifiers": [],
      "rev_accel_score": 0.3,
      "rev_accel_desc": "No Screener data",
      "promoter_score": 0.7,
      "promoter_desc": "\ud83d\udc65 Promoter 74% holding, minimal/no pledge \u2014 won't sell",
      "catalyst_score": 0.1,
      "catalyst_desc": "\u26aa No specific catalyst found in BSE announcements",
      "mcap_score": 0.65,
      "mcap_desc": "\u20b9663Cr \u2014 moderate headroom for 3\u20135x",
      "price_stage_score": 0.65,
      "price_stage_desc": "\ud83d\udfe1 Early uptrend (49% above 52W low, 34% below high)",
      "sector_score": 0.5,
      "sector_desc": "Sector 'Other' not mapped",
      "discovery_score": 1.0,
      "discovery_desc": "\ud83d\udc41\ufe0f UNDISCOVERED: 0.0% institutional \u2014 Lynch sweet spot",
      "sector": "Other",
      "market_cap_cr": 663.2354304
    },
    "piotroski_score": 6,
    "piotroski_01": 0.667,
    "lynch_score": 0.91,
    "debt_score": 1.0,
    "group": null,
    "public_data": {
      "insider_net_shares": 0,
      "insider_buy_count": 0,
      "insider_value_cr": 0.0,
      "promoter_buying": false,
      "insider_score": 0.3,
      "pledge_pct": null,
      "promoter_held_pct": 74.5,
      "is_high_pledge": false,
      "pledge_score": 0.5,
      "has_bulk_deal": false,
      "institutional_buying": false,
      "bulk_net_value_cr": 0.0,
      "bulk_score": 0.3,
      "public_score": 0.36,
      "public_flags": []
    },
    "bse_code": null,
    "announcement_count": 0,
    "concall": {
      "concall_score": 0.3,
      "tier1_signals": [],
      "tier2_signals": [],
      "negative_signals": [],
      "concall_flag": null,
      "manual_review": false,
      "concall_count": 0,
      "has_concall_data": false
    },
    "screener": null,
    "screener_flags": [],
    "screener_roce": null,
    "all_flags": [
      "\ud83d\udc41\ufe0f UNDISCOVERED: 0.0% institutional \u2014 Lynch sweet spot"
    ],
    "persistence": {
      "days_in_watchlist": 12,
      "streak": 0,
      "score_trend": "stable",
      "score_7d_delta": 0.0,
      "first_seen": "20260410",
      "peak_score": 0.541,
      "price_since_first_pct": 18.3,
      "all_catalysts": [
        "\ud83d\udfe2 Deep base (near 52W low, 22% above low)",
        "\ud83d\udc41\ufe0f UNDISCOVERED: 0.0% institutional \u2014 Lynch sweet spot"
      ],
      "latest_catalyst_score": 0.1,
      "latest_dna_score": 0.469
    }
  },
  {
    "symbol": "HPAL.NS",
    "price": 33.58,
    "market_cap_cr": 309.0,
    "avg_volume": 73463,
    "price_stage": "\ud83d\udfe2 DEEP BASE",
    "sector": "Other",
    "composite_score": 0.5407,
    "scanned_at": "2026-07-21T15:44:19.864535",
    "dna": {
      "dna_score": 0.502,
      "dna_grade": "C \u2014 Monitor, not yet actionable",
      "dna_flags": [
        "\ud83d\udfe2 DEEP BASE + coiling (near 52W low, ATR contracted) \u2014 ideal entry zone"
      ],
      "disqualifiers": [],
      "rev_accel_score": 0.3,
      "rev_accel_desc": "No Screener data",
      "promoter_score": 0.7,
      "promoter_desc": "\ud83d\udc65 Promoter 71% holding, minimal/no pledge \u2014 won't sell",
      "catalyst_score": 0.1,
      "catalyst_desc": "\u26aa No specific catalyst found in BSE announcements",
      "mcap_score": 0.85,
      "mcap_desc": "\u20b9309Cr \u2014 good headroom for 5\u201310x",
      "price_stage_score": 1.0,
      "price_stage_desc": "\ud83d\udfe2 DEEP BASE + coiling (near 52W low, ATR contracted) \u2014 ideal entry zone",
      "sector_score": 0.5,
      "sector_desc": "Sector 'Other' not mapped",
      "discovery_score": 0.35,
      "discovery_desc": "Institutional ownership data unavailable",
      "sector": "Other",
      "market_cap_cr": 308.5153792
    },
    "piotroski_score": 7,
    "piotroski_01": 0.778,
    "lynch_score": 0.58,
    "debt_score": 1.0,
    "group": null,
    "public_data": {
      "insider_net_shares": 0,
      "insider_buy_count": 0,
      "insider_value_cr": 0.0,
      "promoter_buying": false,
      "insider_score": 0.3,
      "pledge_pct": null,
      "promoter_held_pct": 71.3,
      "is_high_pledge": false,
      "pledge_score": 0.5,
      "has_bulk_deal": false,
      "institutional_buying": false,
      "bulk_net_value_cr": 0.0,
      "bulk_score": 0.3,
      "public_score": 0.36,
      "public_flags": []
    },
    "bse_code": null,
    "announcement_count": 0,
    "concall": {
      "concall_score": 0.3,
      "tier1_signals": [],
      "tier2_signals": [],
      "negative_signals": [],
      "concall_flag": null,
      "manual_review": false,
      "concall_count": 0,
      "has_concall_data": false
    },
    "screener": null,
    "screener_flags": [],
    "screener_roce": null,
    "all_flags": [
      "\ud83d\udfe2 DEEP BASE + coiling (near 52W low, ATR contracted) \u2014 ideal entry zone"
    ],
    "persistence": {
      "days_in_watchlist": 2,
      "streak": 0,
      "score_trend": "stable",
      "score_7d_delta": 0.005,
      "first_seen": "20260608",
      "peak_score": 0.541,
      "price_since_first_pct": -5.5,
      "all_catalysts": [
        "\ud83d\udfe2 DEEP BASE + coiling (near 52W low, ATR contracted) \u2014 ideal entry zone"
      ],
      "latest_catalyst_score": 0.1,
      "latest_dna_score": 0.502
    }
  },
  {
    "symbol": "ORIENTCER.NS",
    "price": 41.84,
    "market_cap_cr": 501.0,
    "avg_volume": 61114,
    "price_stage": "\ud83d\udfe2 DEEP BASE",
    "sector": "Other",
    "composite_score": 0.5407,
    "scanned_at": "2026-07-21T15:48:51.208025",
    "dna": {
      "dna_score": 0.463,
      "dna_grade": "C \u2014 Monitor, not yet actionable",
      "dna_flags": [
        "\ud83d\udfe2 Deep base (near 52W low, 21% above low)"
      ],
      "disqualifiers": [],
      "rev_accel_score": 0.3,
      "rev_accel_desc": "No Screener data",
      "promoter_score": 0.7,
      "promoter_desc": "\ud83d\udc65 Promoter 80% holding, minimal/no pledge \u2014 won't sell",
      "catalyst_score": 0.1,
      "catalyst_desc": "\u26aa No specific catalyst found in BSE announcements",
      "mcap_score": 0.65,
      "mcap_desc": "\u20b9501Cr \u2014 moderate headroom for 3\u20135x",
      "price_stage_score": 0.85,
      "price_stage_desc": "\ud83d\udfe2 Deep base (near 52W low, 21% above low)",
      "sector_score": 0.5,
      "sector_desc": "Sector 'Other' not mapped",
      "discovery_score": 0.35,
      "discovery_desc": "Institutional ownership data unavailable",
      "sector": "Other",
      "market_cap_cr": 500.5704192
    },
    "piotroski_score": 8,
    "piotroski_01": 0.889,
    "lynch_score": 0.76,
    "debt_score": 0.8,
    "group": null,
    "public_data": {
      "insider_net_shares": 0,
      "insider_buy_count": 0,
      "insider_value_cr": 0.0,
      "promoter_buying": false,
      "insider_score": 0.3,
      "pledge_pct": null,
      "promoter_held_pct": 80.2,
      "is_high_pledge": false,
      "pledge_score": 0.5,
      "has_bulk_deal": false,
      "institutional_buying": false,
      "bulk_net_value_cr": 0.0,
      "bulk_score": 0.3,
      "public_score": 0.36,
      "public_flags": []
    },
    "bse_code": null,
    "announcement_count": 0,
    "concall": {
      "concall_score": 0.3,
      "tier1_signals": [],
      "tier2_signals": [],
      "negative_signals": [],
      "concall_flag": null,
      "manual_review": false,
      "concall_count": 0,
      "has_concall_data": false
    },
    "screener": null,
    "screener_flags": [],
    "screener_roce": null,
    "all_flags": [
      "\ud83d\udfe2 Deep base (near 52W low, 21% above low)"
    ],
    "persistence": {
      "days_in_watchlist": 10,
      "streak": 0,
      "score_trend": "stable",
      "score_7d_delta": 0.0,
      "first_seen": "20260609",
      "peak_score": 0.541,
      "price_since_first_pct": 9.9,
      "all_catalysts": [
        "\ud83d\udfe2 Deep base (near 52W low, 11% above low)",
        "\ud83d\udfe2 Deep base (near 52W low, 16% above low)",
        "\ud83d\udfe2 Deep base (near 52W low, 19% above low)",
        "\ud83d\udfe2 Deep base (near 52W low, 15% above low)",
        "\ud83d\udfe2 Deep base (near 52W low, 17% above low)",
        "\ud83d\udfe2 Deep base (near 52W low, 23% above low)",
        "\ud83d\udfe2 Deep base (near 52W low, 20% above low)",
        "\ud83d\udfe2 Deep base (near 52W low, 21% above low)"
      ],
      "latest_catalyst_score": 0.1,
      "latest_dna_score": 0.463
    }
  }
]